setup.py
NCloudAISDK.egg-info/PKG-INFO
NCloudAISDK.egg-info/SOURCES.txt
NCloudAISDK.egg-info/dependency_links.txt
NCloudAISDK.egg-info/requires.txt
NCloudAISDK.egg-info/top_level.txt
aicloud/__init__.py
aicloud/batch_detection_service.py
aicloud/cloudapi.py
aicloud/cloudexception.py
aicloud/engine.py
aicloud/json_to_coco.py
aicloud/json_to_mapillary.py
aicloud/json_to_voc.py
aicloud/json_to_voc_copy.py
aicloud/rest.py
aicloud/sample.py
aicloud/settings.py
aicloud/utils.py
aicloud/voc_xml_generator.py