Metadata-Version: 1.2
Name: NCloudAISDK
Version: 1.0.1
Summary: NCloudAISDK
Home-page: UNKNOWN
Author: ai
Author-email: example@example.com
License: UNKNOWN
Platform: UNKNOWN
Classifier: Programming Language :: Python :: 3
Classifier: License :: OSI Approved :: MIT License
Classifier: Operating System :: OS Independent
Requires-Python: >=3
